setup.py
blended_html_comment_box.egg-info/PKG-INFO
blended_html_comment_box.egg-info/SOURCES.txt
blended_html_comment_box.egg-info/dependency_links.txt
blended_html_comment_box.egg-info/not-zip-safe
blended_html_comment_box.egg-info/requires.txt
blended_html_comment_box.egg-info/top_level.txt
html_comment_box/__init__.py