Metadata-Version: 1.0
Name: blended-html-comment-box
Version: 1.0
Summary: Easy comments plugin for Blended powered by HTML Comment Box
Home-page: http://jmroper.com/blended/
Author: John Roper
Author-email: johnroper100@gmail.com
License: GPL3.0
Platform: UNKNOWN
